server.py
xls_mcp_servers-1.0.1.dist-info/METADATA
xls_mcp_servers-1.0.1.dist-info/WHEEL
xls_mcp_servers-1.0.1.dist-info/entry_points.txt
xls_mcp_servers-1.0.1.dist-info/top_level.txt
xls_mcp_servers-1.0.1.dist-info/RECORD
