Metadata-Version: 2.4
Name: xls-mcp-servers
Version: 1.0.1
Summary: MCP Server for reading and writing .xls Excel files (Excel 97-2003 binary format)
Author-email: Lincy <1820824481@qq.com>
License: MIT
Project-URL: Homepage, https://github.com/Lincyghb/xls-mcp-server
Project-URL: Documentation, https://github.com/Lincyghb/xls-mcp-server#readme
Project-URL: Repository, https://github.com/Lincyghb/xls-mcp-server
Project-URL: Issues, https://github.com/Lincyghb/xls-mcp-server/issues
Keywords: mcp,excel,xls,model-context-protocol,mcp-server
Classifier: Development Status :: 4 - Beta
Classifier: Intended Audience :: Developers
Classifier: License :: OSI Approved :: MIT License
Classifier: Programming Language :: Python :: 3
Classifier: Programming Language :: Python :: 3.9
Classifier: Programming Language :: Python :: 3.10
Classifier: Programming Language :: Python :: 3.11
Classifier: Programming Language :: Python :: 3.12
Classifier: Topic :: Software Development :: Libraries :: Python Modules
Classifier: Topic :: Office/Business :: Financial :: Spreadsheet
Requires-Python: >=3.9
Requires-Dist: mcp>=1.0.0
Requires-Dist: xlrd>=2.0.1
Requires-Dist: xlwt>=1.3.0
Requires-Dist: xlutils>=2.0.0
